snapshot_restore_py.py
snapshot_restore_py-1.0.0.dist-info/LICENSE
snapshot_restore_py-1.0.0.dist-info/METADATA
snapshot_restore_py-1.0.0.dist-info/WHEEL
snapshot_restore_py-1.0.0.dist-info/top_level.txt
snapshot_restore_py-1.0.0.dist-info/RECORD
