Metadata-Version: 2.1
Name: snapshot-restore-py
Version: 1.0.0
Summary: Runtime Hooks for AWS Lambda SnapStart - Python
Home-page: https://github.com/aws/snapshot-restore-py
Author: Amazon Web Services
License: Apache License 2.0
Keywords: serverless aws lambda python snapstart runtime hooks
Platform: UNKNOWN
Classifier: Development Status :: 5 - Production/Stable
Classifier: Intended Audience :: Developers
Classifier: Natural Language :: English
Classifier: Programming Language :: Python :: 3.12
Classifier: Programming Language :: Python :: 3.13
Classifier: License :: OSI Approved :: Apache Software License
Classifier: Operating System :: OS Independent
Requires-Python: >=3.9
License-File: LICENSE
